{
    "quizIdentity": "football-quiz-1",
    "quizType": "personality",
    "header": {
        "titleText": "Which NG developer are you?"
    },
    "questions": [
        {
            "question": "How does Javascript make you feel?",
            "multiChoiceAnswers": [
                {
                    "answer" : "Elated",
                    "buckets": ["Fabio", "Patrick"]
                },
                {
                    "answer" : "Benign",
                    "buckets": ["Alex", "Stephan"]
                },
                {
                    "answer" : "Furious",
                    "buckets": ["Rob", "John"]
                },
                {
                    "answer" : "Hysterical",
                    "buckets": ["Francis", "Grant"]
                }
            ]
        },
        {
            "question": "How mature do you think you are?",
            "multiChoiceAnswers": [
                {
                    "answer" : "Reasonably high",
                    "buckets": ["John", "Fabio", "Patrick"]
                },
                {
                    "answer" : "Appropriate for my age",
                    "buckets": ["Francis", "Alex"]
                },
                {
                    "answer" : "Disappointingly low, given my age",
                    "buckets": ["Stephan", "Grant"]
                },
                {
                    "answer" : "Barely toddler-level",
                    "buckets": ["Rob"]
                }
            ]
        },
        {
            "question": "T-Shirts... how many conference freebie or \"hilarious\" ones do you own?",
            "multiChoiceAnswers": [
                {
                    "answer" : "They're all I've got in life",
                    "buckets": ["Patrick", "Grant"]
                },
                {
                    "answer" : "A few",
                    "buckets": ["Rob", "Fabio", "John"]
                },
                {
                    "answer" : "None",
                    "buckets": ["Francis", "Alex"]
                },
                {
                    "answer" : "I disdain them utterly",
                    "buckets": ["Stephan"]
                }
            ]
        }
    ],
    "resultBuckets": [
        {
            "title": "Alex",
            "share": "I'm an Alex"
        },
        {
            "title": "John",
            "share": "I'm a John"
        },
        {
            "title": "Francis",
            "share": "I'm a Francis"
        },
        {
            "title": "Rob",
            "share": "I'm a Rob"
        },
        {
            "title": "Stephan",
            "share": "I'm a Stephan"
        },
        {
            "title": "Patrick",
            "share": "I'm a Patrick"
        },
        {
            "title": "Grant",
            "share": "I'm a Grant"
        },
        {
            "title": "Fabio",
            "share": "I'm a Fabio"
        }
    ]
}
